{
"type": "FeatureCollection",
"name": "samples",
"crs": { "type": "name", "properties": { "name": "urn:ogc:def:crs:OGC:1.3:CRS84" } },
"features": [
{ "type": "Feature", "properties": { "point_id": "0b466834ec61", "op_code": "25-19", "period": "S25", "sample_role": "baseline", "trs": "T134N-R82W-S3", "trs_confidence": "exact", "state": "ND", "region": "ND_W", "texture_class": "Loam", "mukey": 2494865.0, "has_dc": true, "has_bd": true, "match_completeness": "full", "latlon_source": "master_a" }, "geometry": { "type": "Point", "coordinates": [ -100.965892, 46.453814 ] } },
{ "type": "Feature", "properties": { "point_id": "5a56d35f6531", "op_code": "25-19", "period": "F25", "sample_role": "monitoring", "trs": "T134N-R82W-S3", "trs_confidence": "exact", "state": "ND", "region": null, "texture_class": "Loam", "mukey": 2494865.0, "has_dc": false, "has_bd": true, "match_completeness": "full_corrected", "latlon_source": "master_2_trs_correction" }, "geometry": { "type": "Point", "coordinates": [ -100.966747, 46.453634 ] } },
{ "type": "Feature", "properties": { "point_id": "5dab71880362", "op_code": "25-19", "period": "F25", "sample_role": "monitoring", "trs": "T135N-R82W-S25", "trs_confidence": "exact", "state": "ND", "region": "ND_W", "texture_class": "Clay Loam", "mukey": 2715035.0, "has_dc": true, "has_bd": true, "match_completeness": "full", "latlon_source": "master_a" }, "geometry": { "type": "Point", "coordinates": [ -100.932606, 46.486703 ] } },
{ "type": "Feature", "properties": { "point_id": "b0d5f669778d", "op_code": "25-19", "period": "F25", "sample_role": "monitoring", "trs": "T138N-R81W-S19", "trs_confidence": "exact", "state": "ND", "region": "ND_W", "texture_class": "Loam", "mukey": 2755731.0, "has_dc": true, "has_bd": true, "match_completeness": "full", "latlon_source": "master_a" }, "geometry": { "type": "Point", "coordinates": [ -100.963669, 46.748617 ] } },
{ "type": "Feature", "properties": { "point_id": "ce0534024321", "op_code": "25-19", "period": "S25", "sample_role": "baseline", "trs": "T135N-R82W-S25", "trs_confidence": "exact", "state": "ND", "region": "ND_W", "texture_class": "Clay Loam", "mukey": 2715035.0, "has_dc": true, "has_bd": true, "match_completeness": "full", "latlon_source": "master_a" }, "geometry": { "type": "Point", "coordinates": [ -100.932606, 46.486703 ] } },
{ "type": "Feature", "properties": { "point_id": "d7aa3c1c17ab", "op_code": "25-19", "period": "F25", "sample_role": "monitoring", "trs": "T134N-R82W-S3", "trs_confidence": "exact", "state": "ND", "region": "ND_W", "texture_class": "Loam", "mukey": 2494865.0, "has_dc": true, "has_bd": false, "match_completeness": "full", "latlon_source": "master_a" }, "geometry": { "type": "Point", "coordinates": [ -100.965892, 46.453814 ] } },
{ "type": "Feature", "properties": { "point_id": "f51cef9d89a7", "op_code": "25-19", "period": "S25", "sample_role": "baseline", "trs": "T138N-R81W-S19", "trs_confidence": "exact", "state": "ND", "region": "ND_W", "texture_class": "Loam", "mukey": 2755731.0, "has_dc": true, "has_bd": true, "match_completeness": "full", "latlon_source": "master_a" }, "geometry": { "type": "Point", "coordinates": [ -100.963669, 46.748617 ] } }
]
}
