{
"type": "FeatureCollection",
"name": "samples",
"crs": { "type": "name", "properties": { "name": "urn:ogc:def:crs:OGC:1.3:CRS84" } },
"features": [
{ "type": "Feature", "properties": { "point_id": "2b0fdfd567b5", "op_code": "25-29", "period": "S25", "sample_role": "baseline", "trs": "T154N-R64W-S10", "trs_confidence": "exact", "state": "ND", "region": "ND_W", "texture_class": "Loam", "mukey": 2587034.0, "has_dc": true, "has_bd": true, "match_completeness": "full", "latlon_source": "master_a" }, "geometry": { "type": "Point", "coordinates": [ -98.863642, 48.178328 ] } },
{ "type": "Feature", "properties": { "point_id": "4d687a73f264", "op_code": "25-29", "period": "F25", "sample_role": "monitoring", "trs": "T154N-R64W-S16", "trs_confidence": "exact", "state": "ND", "region": "ND_W", "texture_class": "Loam", "mukey": 3247758.0, "has_dc": false, "has_bd": true, "match_completeness": "full", "latlon_source": "master_a" }, "geometry": { "type": "Point", "coordinates": [ -98.893828, 48.152428 ] } },
{ "type": "Feature", "properties": { "point_id": "507219d37cca", "op_code": "25-29", "period": "F25", "sample_role": "monitoring", "trs": "T154N-R64W-S10", "trs_confidence": "exact", "state": "ND", "region": "ND_W", "texture_class": "Loam", "mukey": 2587034.0, "has_dc": false, "has_bd": true, "match_completeness": "full", "latlon_source": "master_a" }, "geometry": { "type": "Point", "coordinates": [ -98.863642, 48.178328 ] } },
{ "type": "Feature", "properties": { "point_id": "64c9c088aa74", "op_code": "25-29", "period": "F25", "sample_role": "monitoring", "trs": "T154N-R64W-S4", "trs_confidence": "exact", "state": "ND", "region": "ND_W", "texture_class": "Loam", "mukey": 3247752.0, "has_dc": false, "has_bd": true, "match_completeness": "full", "latlon_source": "master_a" }, "geometry": { "type": "Point", "coordinates": [ -98.879097, 48.194306 ] } },
{ "type": "Feature", "properties": { "point_id": "7572c6c9abe9", "op_code": "25-29", "period": "S25", "sample_role": "baseline", "trs": "T154N-R64W-S16", "trs_confidence": "exact", "state": "ND", "region": "ND_W", "texture_class": "Loam", "mukey": 3247758.0, "has_dc": true, "has_bd": true, "match_completeness": "full", "latlon_source": "master_a" }, "geometry": { "type": "Point", "coordinates": [ -98.893828, 48.152428 ] } },
{ "type": "Feature", "properties": { "point_id": "bfa3ce023a64", "op_code": "25-29", "period": "S25", "sample_role": "baseline", "trs": "T154N-R64W-S4", "trs_confidence": "exact", "state": "ND", "region": "ND_W", "texture_class": "Loam", "mukey": 3247752.0, "has_dc": true, "has_bd": true, "match_completeness": "full", "latlon_source": "master_a" }, "geometry": { "type": "Point", "coordinates": [ -98.879097, 48.194306 ] } }
]
}
