{
"type": "FeatureCollection",
"name": "samples",
"crs": { "type": "name", "properties": { "name": "urn:ogc:def:crs:OGC:1.3:CRS84" } },
"features": [
{ "type": "Feature", "properties": { "point_id": "015e4b3e4b9b", "op_code": "25-50", "period": "F25", "sample_role": "monitoring", "trs": "T148N-R82W-S26", "trs_confidence": "exact", "state": "ND", "region": "ND_W", "texture_class": "Loam", "mukey": 2597002.0, "has_dc": true, "has_bd": true, "match_completeness": "full", "latlon_source": "master_a" }, "geometry": { "type": "Point", "coordinates": [ -101.079167, 47.611489 ] } },
{ "type": "Feature", "properties": { "point_id": "139bb0556efa", "op_code": "25-50", "period": "F25", "sample_role": "monitoring", "trs": "T148N-R82W-S36", "trs_confidence": "exact", "state": "ND", "region": "ND_W", "texture_class": "Loam", "mukey": 2595769.0, "has_dc": true, "has_bd": true, "match_completeness": "full", "latlon_source": "master_a" }, "geometry": { "type": "Point", "coordinates": [ -101.066633, 47.602794 ] } },
{ "type": "Feature", "properties": { "point_id": "2db69a8a4cab", "op_code": "25-50", "period": "S25", "sample_role": "baseline", "trs": "T148N-R82W-S27", "trs_confidence": "exact", "state": "ND", "region": "ND_W", "texture_class": "Loam", "mukey": 2595765.0, "has_dc": true, "has_bd": true, "match_completeness": "full", "latlon_source": "master_a" }, "geometry": { "type": "Point", "coordinates": [ -101.12035, 47.616117 ] } },
{ "type": "Feature", "properties": { "point_id": "48bb6c0c00c0", "op_code": "25-50", "period": "S25", "sample_role": "baseline", "trs": "T148N-R82W-S26", "trs_confidence": "exact", "state": "ND", "region": "ND_W", "texture_class": "Loam", "mukey": 2597002.0, "has_dc": true, "has_bd": true, "match_completeness": "full", "latlon_source": "master_a" }, "geometry": { "type": "Point", "coordinates": [ -101.079167, 47.611489 ] } },
{ "type": "Feature", "properties": { "point_id": "6dd1aa10e0a0", "op_code": "25-50", "period": "S25", "sample_role": "baseline", "trs": "T148N-R82W-S36", "trs_confidence": "exact", "state": "ND", "region": "ND_W", "texture_class": "Loam", "mukey": 2595769.0, "has_dc": true, "has_bd": true, "match_completeness": "full", "latlon_source": "master_a" }, "geometry": { "type": "Point", "coordinates": [ -101.066633, 47.602794 ] } },
{ "type": "Feature", "properties": { "point_id": "d946ee3fd1d9", "op_code": "25-50", "period": "F25", "sample_role": "monitoring", "trs": "T148N-R82W-S27", "trs_confidence": "exact", "state": "ND", "region": "ND_W", "texture_class": "Loam", "mukey": 2595765.0, "has_dc": true, "has_bd": true, "match_completeness": "full", "latlon_source": "master_a" }, "geometry": { "type": "Point", "coordinates": [ -101.12035, 47.616117 ] } }
]
}
