{
"type": "FeatureCollection",
"name": "samples",
"crs": { "type": "name", "properties": { "name": "urn:ogc:def:crs:OGC:1.3:CRS84" } },
"features": [
{ "type": "Feature", "properties": { "point_id": "46c00b8856ac", "op_code": "25-32", "period": "F25", "sample_role": "monitoring", "trs": "T157N-R64W-S20", "trs_confidence": "exact", "state": "ND", "region": "ND_W", "texture_class": "Silty Clay", "mukey": 2587067.0, "has_dc": true, "has_bd": true, "match_completeness": "full", "latlon_source": "master_a" }, "geometry": { "type": "Point", "coordinates": [ -98.948425, 48.413381 ] } },
{ "type": "Feature", "properties": { "point_id": "606dfb09e9ab", "op_code": "25-32", "period": "S25", "sample_role": "baseline", "trs": "T157N-R64W-S29", "trs_confidence": "exact", "state": "ND", "region": "ND_W", "texture_class": "Silty Clay Loam", "mukey": 2585906.0, "has_dc": true, "has_bd": true, "match_completeness": "full", "latlon_source": "master_a" }, "geometry": { "type": "Point", "coordinates": [ -98.948461, 48.394433 ] } },
{ "type": "Feature", "properties": { "point_id": "74372685449d", "op_code": "25-32", "period": "S25", "sample_role": "baseline", "trs": "T157N-R64W-S20", "trs_confidence": "exact", "state": "ND", "region": "ND_W", "texture_class": "Silty Clay", "mukey": 2587067.0, "has_dc": true, "has_bd": true, "match_completeness": "full", "latlon_source": "master_a" }, "geometry": { "type": "Point", "coordinates": [ -98.948425, 48.413381 ] } },
{ "type": "Feature", "properties": { "point_id": "c74720eddd55", "op_code": "25-32", "period": "F25", "sample_role": "monitoring", "trs": "T157N-R64W-S29", "trs_confidence": "exact", "state": "ND", "region": "ND_W", "texture_class": "Silty Clay Loam", "mukey": 2585906.0, "has_dc": true, "has_bd": true, "match_completeness": "full", "latlon_source": "master_a" }, "geometry": { "type": "Point", "coordinates": [ -98.948461, 48.394433 ] } }
]
}
